MANIFEST.in
README.rst
setup.cfg
setup.py
src/socib/__init__.py
src/socib/test_example resource_webpage.py
src/socib/test_example_onlyone_resource_type.py
src/socib/resource_catalog/__init__.py
src/socib/resource_catalog/annotations.py
src/socib/resource_catalog/config.py
src/socib/resource_catalog/namespace.py
src/socib/resource_catalog/utils.py
src/socib/resource_catalog/models/__init__.py
src/socib/resource_catalog/models/address.py
src/socib/resource_catalog/models/api.py
src/socib/resource_catalog/models/api_operation.py
src/socib/resource_catalog/models/base.py
src/socib/resource_catalog/models/catalog.py
src/socib/resource_catalog/models/concept.py
src/socib/resource_catalog/models/concept_scheme.py
src/socib/resource_catalog/models/contact_point.py
src/socib/resource_catalog/models/dataset.py
src/socib/resource_catalog/models/distribution.py
src/socib/resource_catalog/models/document.py
src/socib/resource_catalog/models/equipment.py
src/socib/resource_catalog/models/facility.py
src/socib/resource_catalog/models/frequency.py
src/socib/resource_catalog/models/organization.py
src/socib/resource_catalog/models/person.py
src/socib/resource_catalog/models/platform.py
src/socib/resource_catalog/models/program.py
src/socib/resource_catalog/models/project.py
src/socib/resource_catalog/models/relation.py
src/socib/resource_catalog/models/resource.py
src/socib/resource_catalog/models/sensor.py
src/socib/resource_catalog/models/service.py
src/socib/resource_catalog/models/software.py
src/socib/resource_catalog/models/software_source.py
src/socib/resource_catalog/models/spatial.py
src/socib/resource_catalog/models/temporal.py
src/socib/resource_catalog/models/text.py
src/socib/resource_catalog/models/variable.py
src/socib/resource_catalog/models/vcard.py
src/socib/resource_catalog/models/webpage.py
src/socib/resource_catalog/models/webservice.py
src/socib/resource_catalog/models/website.py
src/socib_resource_catalog_neo4j.egg-info/PKG-INFO
src/socib_resource_catalog_neo4j.egg-info/SOURCES.txt
src/socib_resource_catalog_neo4j.egg-info/dependency_links.txt
src/socib_resource_catalog_neo4j.egg-info/requires.txt
src/socib_resource_catalog_neo4j.egg-info/top_level.txt